gtdata2/__init__.py
gtdata2-0.1.0.dist-info/METADATA
gtdata2-0.1.0.dist-info/WHEEL
gtdata2-0.1.0.dist-info/RECORD
