Metadata-Version: 2.1
Name: gtdata2
Version: 0.1.0
Summary: Add your description here
Author-email: kyrie1218 <kyrie1218@163.com>
Requires-Python: >=3.8
Requires-Dist: numpy>=1.24.4
Requires-Dist: pandas>=2.0.3
Requires-Dist: pydantic>=2.3.0
Requires-Dist: typeguard>=4.1.5
